{
  "constants": {
    "OBJETOIMPUESTO": "02"
  },
  "program": {
    "inpDir": "c:\\c_portab\\01_rb\\_rbprogs\\go-cp2xlsc\\",
    "outDir": "c:\\c_portab\\01_rb\\_rbprogs\\go-cp2xlsc\\",
    "filDir": "c:\\c_portab\\01_rb\\_rbprogs\\go-cp2xlsc\\",
    "inFilt": "!(*processed*)",
    "inName": "rundt+'_'+ifiln+'_inp_processed'",
    "ouName": "rundt+'_'+ifiln+'_out'"
  },
  "run": [
    {
      "option": "txc", "objNam": "edicom-bbm", "mode": "INDIV", "output": "FULL",
      "inpFil": "edicom-bbm.xlsx",
      "inpDir": "c:\\c_portab\\01_rb\\ProgramData\\go-cp2xlsc\\edicom-bbm\\input\\",
      "outDir": "c:\\c_portab\\01_rb\\ProgramData\\go-cp2xlsc\\edicom-bbm\\output\\"
    },
    {
      "option": "txc", "objNam": "edicom-dc",  "mode": "INDIV", "output": "FULL",
      "inpFil": "edicom-dc.xlsx",
      "inpDir": "c:\\c_portab\\01_rb\\ProgramData\\go-cp2xlsc\\edicom-dc\\input\\",
      "outDir": "c:\\c_portab\\01_rb\\ProgramData\\go-cp2xlsc\\edicom-dc\\output\\"
    }
  ]
}
